remote_slurm_spawner/__init__.py
remote_slurm_spawner/api.py
remote_slurm_spawner/remote_slurm_spawner.py
remote_slurm_spawner/singleuser.py
remote_slurm_spawner-0.1.2.dev0.data/scripts/batchspawner-singleuser
remote_slurm_spawner-0.1.2.dev0.dist-info/LICENSE
remote_slurm_spawner-0.1.2.dev0.dist-info/METADATA
remote_slurm_spawner-0.1.2.dev0.dist-info/WHEEL
remote_slurm_spawner-0.1.2.dev0.dist-info/top_level.txt
remote_slurm_spawner-0.1.2.dev0.dist-info/RECORD
