Metadata-Version: 2.1
Name: remote-slurm-spawner
Version: 0.1.2.dev0
Summary: Remote-slurm-spawner: A spawner for Jupyterhub to spawn notebooks using slurm on remote machine.
Home-page: http://jupyter.org
Author: D. Ciangottini, credits to Michael Milligan, Andrea Zonca, Mike Gilbert
Author-email: dciangot@cern.ch
License: BSD
Keywords: Interactive,Interpreter,Shell,Web,Jupyter
Platform: Linux
Platform: Mac OS X
Requires-Python: ~=3.3
Requires-Dist: async-generator (>=1.8)
Requires-Dist: jinja2
Requires-Dist: jupyterhub (>=0.5)
Requires-Dist: paramiko
Requires-Dist: pycurl
Requires-Dist: pytest
